pyweboverlay/__init__.py
pyweboverlay/core.py
pyweboverlay/overlay.py
pyweboverlay/template.html
pyweboverlay-1.0.6.dist-info/licenses/LICENSE
pyweboverlay-1.0.6.dist-info/METADATA
pyweboverlay-1.0.6.dist-info/WHEEL
pyweboverlay-1.0.6.dist-info/top_level.txt
pyweboverlay-1.0.6.dist-info/RECORD
