Metadata-Version: 2.4
Name: pyweboverlay
Version: 1.0.6
Summary: A Python package for creating simple local web overlays for streams and other needs
Author: chrisrca
License: Copyright 2025 chrisrca
Project-URL: Repository, https://github.com/chrisrca/pyweboverlay
Keywords: overlay,web,obs
Classifier: Programming Language :: Python :: 3.9
Classifier: License :: OSI Approved :: MIT License
Classifier: Operating System :: OS Independent
Requires-Python: ==3.9.*
License-File: LICENSE
Requires-Dist: Flask==3.1.2
Requires-Dist: flask-socketio==5.3.6
Requires-Dist: requests==2.32.5
Dynamic: license-file
